mobio/libs/validator/__init__.py
mobio/libs/validator/message_en.json
mobio/libs/validator/message_vi.json
m_validator-0.1.dist-info/METADATA
m_validator-0.1.dist-info/WHEEL
m_validator-0.1.dist-info/top_level.txt
m_validator-0.1.dist-info/RECORD
