Metadata-Version: 2.1
Name: m-validator
Version: 0.1
Summary: Thư viện validate dữ liệu đầu vào
Home-page: https://github.com/mobiovn
Author: MOBIO
Author-email: contact@mobio.vn
License: MIT
Platform: UNKNOWN
Provides-Extra: get_lang_from_request
Requires-Dist: flask ; extra == 'get_lang_from_request'
